pycompomics/__init__.py
pycompomics/pycompomics.py
pycompomics-0.0.dist-info/LICENSE
pycompomics-0.0.dist-info/METADATA
pycompomics-0.0.dist-info/WHEEL
pycompomics-0.0.dist-info/top_level.txt
pycompomics-0.0.dist-info/RECORD
