Metadata-Version: 2.1
Name: pycompomics
Version: 0.0
Summary: wrapper for the Compomics suite of MS tools
Home-page: UNKNOWN
Author: sebastien Leblanc
Author-email: sebastien.leblanc5@usherbrooke.ca
License: MIT
Platform: UNKNOWN
Requires-Python: >=3.6
